odoo/addons/repair_reason/README.rst
odoo/addons/repair_reason/__init__.py
odoo/addons/repair_reason/__manifest__.py
odoo/addons/repair_reason/i18n/it.po
odoo/addons/repair_reason/i18n/repair_reason.pot
odoo/addons/repair_reason/models/__init__.py
odoo/addons/repair_reason/models/repair_order.py
odoo/addons/repair_reason/models/repair_reason.py
odoo/addons/repair_reason/readme/CONTRIBUTORS.rst
odoo/addons/repair_reason/readme/DESCRIPTION.rst
odoo/addons/repair_reason/readme/USAGE.rst
odoo/addons/repair_reason/security/ir.model.access.csv
odoo/addons/repair_reason/static/description/icon.png
odoo/addons/repair_reason/static/description/index.html
odoo/addons/repair_reason/tests/__init__.py
odoo/addons/repair_reason/tests/test_repair_reason.py
odoo/addons/repair_reason/views/repair_order_view.xml
odoo/addons/repair_reason/views/repair_reason_view.xml
odoo_addon_repair_reason-16.0.1.0.0.4.dist-info/METADATA
odoo_addon_repair_reason-16.0.1.0.0.4.dist-info/WHEEL
odoo_addon_repair_reason-16.0.1.0.0.4.dist-info/top_level.txt
odoo_addon_repair_reason-16.0.1.0.0.4.dist-info/RECORD
